{
    "m_Version": 12,
    "DisplayName": "APES",
    "Icon": "Deliver",
    "Color": "FBFCFEFF",
    "IsExchange": 0,
    "InitStockPercent": 75.0,
    "Items": [
        {
            "ClassName": "APES_Hunting_Aqua",
            "MaxPriceThreshold": 7500,
            "MinPriceThreshold": 7500,
            "SellPricePercent": -1.0,
            "MaxStockThreshold": -1,
            "MinStockThreshold": -1,
            "QuantityPercent": -1,
            "SpawnAttachments": [],
            "Variants": []
        },
        {
            "ClassName": "APES_Hunting_Black",
            "MaxPriceThreshold": 7500,
            "MinPriceThreshold": 7500,
            "SellPricePercent": -1.0,
            "MaxStockThreshold": -1,
            "MinStockThreshold": -1,
            "QuantityPercent": -1,
            "SpawnAttachments": [],
            "Variants": []
        },
        {
            "ClassName": "APES_Hunting_Blue",
            "MaxPriceThreshold": 7500,
            "MinPriceThreshold": 7500,
            "SellPricePercent": -1.0,
            "MaxStockThreshold": -1,
            "MinStockThreshold": -1,
            "QuantityPercent": -1,
            "SpawnAttachments": [],
            "Variants": []
        },
        {
            "ClassName": "APES_Hunting_CCE",
            "MaxPriceThreshold": 7500,
            "MinPriceThreshold": 7500,
            "SellPricePercent": -1.0,
            "MaxStockThreshold": -1,
            "MinStockThreshold": -1,
            "QuantityPercent": -1,
            "SpawnAttachments": [],
            "Variants": []
        },
        {
            "ClassName": "APES_Hunting_Green",
            "MaxPriceThreshold": 7500,
            "MinPriceThreshold": 7500,
            "SellPricePercent": -1.0,
            "MaxStockThreshold": -1,
            "MinStockThreshold": -1,
            "QuantityPercent": -1,
            "SpawnAttachments": [],
            "Variants": []
        },
        {
            "ClassName": "APES_Hunting_Pink",
            "MaxPriceThreshold": 7500,
            "MinPriceThreshold": 7500,
            "SellPricePercent": -1.0,
            "MaxStockThreshold": -1,
            "MinStockThreshold": -1,
            "QuantityPercent": -1,
            "SpawnAttachments": [],
            "Variants": []
        },
        {
            "ClassName": "APES_Hunting_Red",
            "MaxPriceThreshold": 7500,
            "MinPriceThreshold": 7500,
            "SellPricePercent": -1.0,
            "MaxStockThreshold": -1,
            "MinStockThreshold": -1,
            "QuantityPercent": -1,
            "SpawnAttachments": [],
            "Variants": []
        },
        {
            "ClassName": "APES_Hunting_Yellow",
            "MaxPriceThreshold": 7500,
            "MinPriceThreshold": 7500,
            "SellPricePercent": -1.0,
            "MaxStockThreshold": -1,
            "MinStockThreshold": -1,
            "QuantityPercent": -1,
            "SpawnAttachments": [],
            "Variants": []
        },
        {
            "ClassName": "APES_Mildot",
            "MaxPriceThreshold": 7500,
            "MinPriceThreshold": 7500,
            "SellPricePercent": -1.0,
            "MaxStockThreshold": -1,
            "MinStockThreshold": -1,
            "QuantityPercent": -1,
            "SpawnAttachments": [],
            "Variants": []
        },
        {
            "ClassName": "APES_Shinigami_Base",
            "MaxPriceThreshold": 7500,
            "MinPriceThreshold": 7500,
            "SellPricePercent": -1.0,
            "MaxStockThreshold": -1,
            "MinStockThreshold": -1,
            "QuantityPercent": -1,
            "SpawnAttachments": [],
            "Variants": []
        },
        {
            "ClassName": "APES_Shinigami_V2_Aqua",
            "MaxPriceThreshold": 7500,
            "MinPriceThreshold": 7500,
            "SellPricePercent": -1.0,
            "MaxStockThreshold": -1,
            "MinStockThreshold": -1,
            "QuantityPercent": -1,
            "SpawnAttachments": [],
            "Variants": []
        },
        {
            "ClassName": "APES_Shinigami_V2_Black",
            "MaxPriceThreshold": 7500,
            "MinPriceThreshold": 7500,
            "SellPricePercent": -1.0,
            "MaxStockThreshold": -1,
            "MinStockThreshold": -1,
            "QuantityPercent": -1,
            "SpawnAttachments": [],
            "Variants": []
        },
        {
            "ClassName": "APES_Shinigami_V2_Blue",
            "MaxPriceThreshold": 7500,
            "MinPriceThreshold": 7500,
            "SellPricePercent": -1.0,
            "MaxStockThreshold": -1,
            "MinStockThreshold": -1,
            "QuantityPercent": -1,
            "SpawnAttachments": [],
            "Variants": []
        },
        {
            "ClassName": "APES_Shinigami_V2_Green",
            "MaxPriceThreshold": 7500,
            "MinPriceThreshold": 7500,
            "SellPricePercent": -1.0,
            "MaxStockThreshold": -1,
            "MinStockThreshold": -1,
            "QuantityPercent": -1,
            "SpawnAttachments": [],
            "Variants": []
        },
        {
            "ClassName": "APES_Shinigami_V2_Pink",
            "MaxPriceThreshold": 7500,
            "MinPriceThreshold": 7500,
            "SellPricePercent": -1.0,
            "MaxStockThreshold": -1,
            "MinStockThreshold": -1,
            "QuantityPercent": -1,
            "SpawnAttachments": [],
            "Variants": []
        },
        {
            "ClassName": "APES_Shinigami_V2_Red",
            "MaxPriceThreshold": 7500,
            "MinPriceThreshold": 7500,
            "SellPricePercent": -1.0,
            "MaxStockThreshold": -1,
            "MinStockThreshold": -1,
            "QuantityPercent": -1,
            "SpawnAttachments": [],
            "Variants": []
        },
        {
            "ClassName": "APES_Shinigami_V2_Yellow",
            "MaxPriceThreshold": 7500,
            "MinPriceThreshold": 7500,
            "SellPricePercent": -1.0,
            "MaxStockThreshold": -1,
            "MinStockThreshold": -1,
            "QuantityPercent": -1,
            "SpawnAttachments": [],
            "Variants": []
        },
        {
            "ClassName": "APES_Shinigamiaqua",
            "MaxPriceThreshold": 7500,
            "MinPriceThreshold": 7500,
            "SellPricePercent": -1.0,
            "MaxStockThreshold": -1,
            "MinStockThreshold": -1,
            "QuantityPercent": -1,
            "SpawnAttachments": [],
            "Variants": []
        },
        {
            "ClassName": "APES_Shinigamiblack",
            "MaxPriceThreshold": 7500,
            "MinPriceThreshold": 7500,
            "SellPricePercent": -1.0,
            "MaxStockThreshold": -1,
            "MinStockThreshold": -1,
            "QuantityPercent": -1,
            "SpawnAttachments": [],
            "Variants": []
        },
        {
            "ClassName": "APES_Shinigamiblue",
            "MaxPriceThreshold": 7500,
            "MinPriceThreshold": 7500,
            "SellPricePercent": -1.0,
            "MaxStockThreshold": -1,
            "MinStockThreshold": -1,
            "QuantityPercent": -1,
            "SpawnAttachments": [],
            "Variants": []
        },
        {
            "ClassName": "APES_Shinigamigreen",
            "MaxPriceThreshold": 7500,
            "MinPriceThreshold": 7500,
            "SellPricePercent": -1.0,
            "MaxStockThreshold": -1,
            "MinStockThreshold": -1,
            "QuantityPercent": -1,
            "SpawnAttachments": [],
            "Variants": []
        },
        {
            "ClassName": "APES_Shinigamipink",
            "MaxPriceThreshold": 7500,
            "MinPriceThreshold": 7500,
            "SellPricePercent": -1.0,
            "MaxStockThreshold": -1,
            "MinStockThreshold": -1,
            "QuantityPercent": -1,
            "SpawnAttachments": [],
            "Variants": []
        },
        {
            "ClassName": "APES_Shinigamired",
            "MaxPriceThreshold": 7500,
            "MinPriceThreshold": 7500,
            "SellPricePercent": -1.0,
            "MaxStockThreshold": -1,
            "MinStockThreshold": -1,
            "QuantityPercent": -1,
            "SpawnAttachments": [],
            "Variants": []
        },
        {
            "ClassName": "APES_Shinigamiyellow",
            "MaxPriceThreshold": 7500,
            "MinPriceThreshold": 7500,
            "SellPricePercent": -1.0,
            "MaxStockThreshold": -1,
            "MinStockThreshold": -1,
            "QuantityPercent": -1,
            "SpawnAttachments": [],
            "Variants": []
        },
        {
            "ClassName": "APES_Shortdot_Base",
            "MaxPriceThreshold": 7500,
            "MinPriceThreshold": 7500,
            "SellPricePercent": -1.0,
            "MaxStockThreshold": -1,
            "MinStockThreshold": -1,
            "QuantityPercent": -1,
            "SpawnAttachments": [],
            "Variants": []
        },
        {
            "ClassName": "APES_Shortdotaqua",
            "MaxPriceThreshold": 7500,
            "MinPriceThreshold": 7500,
            "SellPricePercent": -1.0,
            "MaxStockThreshold": -1,
            "MinStockThreshold": -1,
            "QuantityPercent": -1,
            "SpawnAttachments": [],
            "Variants": []
        },
        {
            "ClassName": "APES_Shortdotblue",
            "MaxPriceThreshold": 7500,
            "MinPriceThreshold": 7500,
            "SellPricePercent": -1.0,
            "MaxStockThreshold": -1,
            "MinStockThreshold": -1,
            "QuantityPercent": -1,
            "SpawnAttachments": [],
            "Variants": []
        },
        {
            "ClassName": "APES_Shortdotgreen",
            "MaxPriceThreshold": 7500,
            "MinPriceThreshold": 7500,
            "SellPricePercent": -1.0,
            "MaxStockThreshold": -1,
            "MinStockThreshold": -1,
            "QuantityPercent": -1,
            "SpawnAttachments": [],
            "Variants": []
        },
        {
            "ClassName": "APES_Shortdotpink",
            "MaxPriceThreshold": 7500,
            "MinPriceThreshold": 7500,
            "SellPricePercent": -1.0,
            "MaxStockThreshold": -1,
            "MinStockThreshold": -1,
            "QuantityPercent": -1,
            "SpawnAttachments": [],
            "Variants": []
        },
        {
            "ClassName": "APES_Shortdotred",
            "MaxPriceThreshold": 7500,
            "MinPriceThreshold": 7500,
            "SellPricePercent": -1.0,
            "MaxStockThreshold": -1,
            "MinStockThreshold": -1,
            "QuantityPercent": -1,
            "SpawnAttachments": [],
            "Variants": []
        },
        {
            "ClassName": "APES_Shortdotyellow",
            "MaxPriceThreshold": 7500,
            "MinPriceThreshold": 7500,
            "SellPricePercent": -1.0,
            "MaxStockThreshold": -1,
            "MinStockThreshold": -1,
            "QuantityPercent": -1,
            "SpawnAttachments": [],
            "Variants": []
        }
    ]
}